[
{
  "elements": [
    {
      "keyword": "Scenario", 
      "location": "features/StockSearchDisplay.feature:4", 
      "name": "Verify stock info display correct symbol", 
      "steps": [
        {
          "keyword": "Given", 
          "location": "features/StockSearchDisplay.feature:5", 
          "match": {
            "arguments": [
              {
                "name": "PageName", 
                "value": "SettradeHomePage"
              }
            ], 
            "location": "../project-cylon/project_cylon/CommonSteps.py:8"
          }, 
          "name": "User has [SettradeHomePage] open", 
          "result": {
            "duration": 3.155539035797119, 
            "status": "passed"
          }, 
          "step_type": "given"
        }, 
        {
          "keyword": "And", 
          "location": "features/StockSearchDisplay.feature:6", 
          "match": {
            "arguments": [
              {
                "name": "Amount", 
                "value": "99"
              }, 
              {
                "name": "ElementName", 
                "value": "images"
              }
            ], 
            "location": "../project-cylon/project_cylon/CommonSteps.py:205"
          }, 
          "name": "The system displays '99' items of [images]", 
          "result": {
            "duration": 0.19970703125, 
            "error_message": [
              "Traceback (most recent call last):", 
              "  File \"/usr/local/Cellar/python/2.7.6/Frameworks/Python.framework/Versions/2.7/lib/python2.7/site-packages/behave/model.py\", line 1173, in run", 
              "    match.run(runner.context)", 
              "  File \"/usr/local/Cellar/python/2.7.6/Frameworks/Python.framework/Versions/2.7/lib/python2.7/site-packages/behave/model.py\", line 1589, in run", 
              "    self.func(context, *args, **kwargs)", 
              "  File \"/Users/Peerapat/Works/github/project-cylon/project_cylon/CommonSteps.py\", line 209, in step", 
              "    Element.VerifyItemsCount(Amount)", 
              "  File \"/Users/Peerapat/Works/github/project-cylon/project_cylon/PageObject.py\", line 231, in VerifyItemsCount", 
              "    Log.Failed(\"Verify elements count '%s'\" % self.name, self.Count, count)", 
              "  File \"/Users/Peerapat/Works/github/project-cylon/project_cylon/Logger.py\", line 56, in Failed", 
              "    raise \"(Failed)\"", 
              "TypeError: exceptions must be old-style classes or derived from BaseException, not str", 
              "", 
              "Captured stdout:", 
              "Verify elements count 'images'", 
              "actual: '104'", 
              "expect: '99'", 
              ""
            ], 
            "status": "failed"
          }, 
          "step_type": "given"
        }, 
        {
          "keyword": "When", 
          "location": "features/StockSearchDisplay.feature:7", 
          "name": "User enters 'ICHI' to [txt_symbol]", 
          "step_type": "when"
        }, 
        {
          "keyword": "And", 
          "location": "features/StockSearchDisplay.feature:8", 
          "name": "User clicks [btn_search] link", 
          "step_type": "when"
        }, 
        {
          "keyword": "Then", 
          "location": "features/StockSearchDisplay.feature:9", 
          "name": "The system displays [StockInfoPage]", 
          "step_type": "then"
        }, 
        {
          "keyword": "And", 
          "location": "features/StockSearchDisplay.feature:10", 
          "name": "The [div_symbol] shows 'ICHI'", 
          "step_type": "then"
        }
      ], 
      "tags": [
        "basic"
      ], 
      "type": "scenario"
    }, 
    {
      "keyword": "Scenario Outline", 
      "location": "features/StockSearchDisplay.feature:13", 
      "name": "Verify stock info display correct symbol, last price is between floor and ceil", 
      "steps": [
        {
          "keyword": "Given", 
          "location": "features/StockSearchDisplay.feature:14", 
          "match": {
            "arguments": [
              {
                "name": "PageName", 
                "value": "SettradeHomePage"
              }
            ], 
            "location": "../project-cylon/project_cylon/CommonSteps.py:8"
          }, 
          "name": "User has [SettradeHomePage] open", 
          "result": {
            "duration": 0.0630340576171875, 
            "status": "passed"
          }, 
          "step_type": "given"
        }, 
        {
          "keyword": "When", 
          "location": "features/StockSearchDisplay.feature:15", 
          "match": {
            "arguments": [
              {
                "name": "Value", 
                "value": "ADVANC"
              }, 
              {
                "name": "ElementName", 
                "value": "txt_symbol"
              }
            ], 
            "location": "../project-cylon/project_cylon/CommonSteps.py:16"
          }, 
          "name": "User enters 'ADVANC' to [txt_symbol]", 
          "result": {
            "duration": 3.0204010009765625, 
            "status": "passed"
          }, 
          "step_type": "when"
        }, 
        {
          "keyword": "And", 
          "location": "features/StockSearchDisplay.feature:16", 
          "match": {
            "arguments": [
              {
                "name": "ElementName", 
                "value": "btn_search"
              }
            ], 
            "location": "../project-cylon/project_cylon/CommonSteps.py:34"
          }, 
          "name": "User clicks [btn_search] link", 
          "result": {
            "duration": 1.5916249752044678, 
            "status": "passed"
          }, 
          "step_type": "when"
        }, 
        {
          "keyword": "Then", 
          "location": "features/StockSearchDisplay.feature:17", 
          "match": {
            "arguments": [
              {
                "name": "PageName", 
                "value": "StockInfoPage"
              }
            ], 
            "location": "../project-cylon/project_cylon/CommonSteps.py:76"
          }, 
          "name": "The system displays [StockInfoPage]", 
          "result": {
            "duration": 0.03484487533569336, 
            "status": "passed"
          }, 
          "step_type": "then"
        }, 
        {
          "keyword": "And", 
          "location": "features/StockSearchDisplay.feature:18", 
          "match": {
            "arguments": [
              {
                "name": "ElementName", 
                "value": "div_symbol"
              }, 
              {
                "name": "Value", 
                "value": "ADVANC"
              }
            ], 
            "location": "../project-cylon/project_cylon/CommonSteps.py:103"
          }, 
          "name": "The [div_symbol] shows 'ADVANC'", 
          "result": {
            "duration": 0.016594886779785156, 
            "status": "passed"
          }, 
          "step_type": "then"
        }, 
        {
          "keyword": "And", 
          "location": "features/StockSearchDisplay.feature:19", 
          "match": {
            "arguments": [
              {
                "name": "ElementName", 
                "value": "div_price"
              }, 
              {
                "name": "Value", 
                "value": "171.00"
              }
            ], 
            "location": "../project-cylon/project_cylon/CommonSteps.py:117"
          }, 
          "name": "The [div_price] more than '171.00'", 
          "result": {
            "duration": 0.016352176666259766, 
            "status": "passed"
          }, 
          "step_type": "then"
        }, 
        {
          "keyword": "And", 
          "location": "features/StockSearchDisplay.feature:20", 
          "match": {
            "arguments": [
              {
                "name": "ElementName", 
                "value": "div_price"
              }, 
              {
                "name": "Value", 
                "value": "317.00"
              }
            ], 
            "location": "../project-cylon/project_cylon/CommonSteps.py:131"
          }, 
          "name": "The [div_price] less than '317.00'", 
          "result": {
            "duration": 0.03666806221008301, 
            "status": "passed"
          }, 
          "step_type": "then"
        }
      ], 
      "tags": [
        "outline"
      ], 
      "type": "scenario"
    }, 
    {
      "keyword": "Scenario Outline", 
      "location": "features/StockSearchDisplay.feature:13", 
      "name": "Verify stock info display correct symbol, last price is between floor and ceil", 
      "steps": [
        {
          "keyword": "Given", 
          "location": "features/StockSearchDisplay.feature:14", 
          "match": {
            "arguments": [
              {
                "name": "PageName", 
                "value": "SettradeHomePage"
              }
            ], 
            "location": "../project-cylon/project_cylon/CommonSteps.py:8"
          }, 
          "name": "User has [SettradeHomePage] open", 
          "result": {
            "duration": 2.8827171325683594, 
            "status": "passed"
          }, 
          "step_type": "given"
        }, 
        {
          "keyword": "When", 
          "location": "features/StockSearchDisplay.feature:15", 
          "match": {
            "arguments": [
              {
                "name": "Value", 
                "value": "INTUCH"
              }, 
              {
                "name": "ElementName", 
                "value": "txt_symbol"
              }
            ], 
            "location": "../project-cylon/project_cylon/CommonSteps.py:16"
          }, 
          "name": "User enters 'INTUCH' to [txt_symbol]", 
          "result": {
            "duration": 0.14802193641662598, 
            "status": "passed"
          }, 
          "step_type": "when"
        }, 
        {
          "keyword": "And", 
          "location": "features/StockSearchDisplay.feature:16", 
          "match": {
            "arguments": [
              {
                "name": "ElementName", 
                "value": "btn_search"
              }
            ], 
            "location": "../project-cylon/project_cylon/CommonSteps.py:34"
          }, 
          "name": "User clicks [btn_search] link", 
          "result": {
            "duration": 1.2879478931427002, 
            "status": "passed"
          }, 
          "step_type": "when"
        }, 
        {
          "keyword": "Then", 
          "location": "features/StockSearchDisplay.feature:17", 
          "match": {
            "arguments": [
              {
                "name": "PageName", 
                "value": "StockInfoPage"
              }
            ], 
            "location": "../project-cylon/project_cylon/CommonSteps.py:76"
          }, 
          "name": "The system displays [StockInfoPage]", 
          "result": {
            "duration": 0.023853778839111328, 
            "status": "passed"
          }, 
          "step_type": "then"
        }, 
        {
          "keyword": "And", 
          "location": "features/StockSearchDisplay.feature:18", 
          "match": {
            "arguments": [
              {
                "name": "ElementName", 
                "value": "div_symbol"
              }, 
              {
                "name": "Value", 
                "value": "INTUCH"
              }
            ], 
            "location": "../project-cylon/project_cylon/CommonSteps.py:103"
          }, 
          "name": "The [div_symbol] shows 'INTUCH'", 
          "result": {
            "duration": 0.02190399169921875, 
            "status": "passed"
          }, 
          "step_type": "then"
        }, 
        {
          "keyword": "And", 
          "location": "features/StockSearchDisplay.feature:19", 
          "match": {
            "arguments": [
              {
                "name": "ElementName", 
                "value": "div_price"
              }, 
              {
                "name": "Value", 
                "value": "55.00"
              }
            ], 
            "location": "../project-cylon/project_cylon/CommonSteps.py:117"
          }, 
          "name": "The [div_price] more than '55.00'", 
          "result": {
            "duration": 0.03306913375854492, 
            "status": "passed"
          }, 
          "step_type": "then"
        }, 
        {
          "keyword": "And", 
          "location": "features/StockSearchDisplay.feature:20", 
          "match": {
            "arguments": [
              {
                "name": "ElementName", 
                "value": "div_price"
              }, 
              {
                "name": "Value", 
                "value": "99.00"
              }
            ], 
            "location": "../project-cylon/project_cylon/CommonSteps.py:131"
          }, 
          "name": "The [div_price] less than '99.00'", 
          "result": {
            "duration": 0.03991413116455078, 
            "status": "passed"
          }, 
          "step_type": "then"
        }
      ], 
      "tags": [
        "outline"
      ], 
      "type": "scenario"
    }, 
    {
      "keyword": "Scenario Outline", 
      "location": "features/StockSearchDisplay.feature:13", 
      "name": "Verify stock info display correct symbol, last price is between floor and ceil", 
      "steps": [
        {
          "keyword": "Given", 
          "location": "features/StockSearchDisplay.feature:14", 
          "match": {
            "arguments": [
              {
                "name": "PageName", 
                "value": "SettradeHomePage"
              }
            ], 
            "location": "../project-cylon/project_cylon/CommonSteps.py:8"
          }, 
          "name": "User has [SettradeHomePage] open", 
          "result": {
            "duration": 3.0073299407958984, 
            "status": "passed"
          }, 
          "step_type": "given"
        }, 
        {
          "keyword": "When", 
          "location": "features/StockSearchDisplay.feature:15", 
          "match": {
            "arguments": [
              {
                "name": "Value", 
                "value": "MCOT"
              }, 
              {
                "name": "ElementName", 
                "value": "txt_symbol"
              }
            ], 
            "location": "../project-cylon/project_cylon/CommonSteps.py:16"
          }, 
          "name": "User enters 'MCOT' to [txt_symbol]", 
          "result": {
            "duration": 0.15657901763916016, 
            "status": "passed"
          }, 
          "step_type": "when"
        }, 
        {
          "keyword": "And", 
          "location": "features/StockSearchDisplay.feature:16", 
          "match": {
            "arguments": [
              {
                "name": "ElementName", 
                "value": "btn_search"
              }
            ], 
            "location": "../project-cylon/project_cylon/CommonSteps.py:34"
          }, 
          "name": "User clicks [btn_search] link", 
          "result": {
            "duration": 1.7397220134735107, 
            "status": "passed"
          }, 
          "step_type": "when"
        }, 
        {
          "keyword": "Then", 
          "location": "features/StockSearchDisplay.feature:17", 
          "match": {
            "arguments": [
              {
                "name": "PageName", 
                "value": "StockInfoPage"
              }
            ], 
            "location": "../project-cylon/project_cylon/CommonSteps.py:76"
          }, 
          "name": "The system displays [StockInfoPage]", 
          "result": {
            "duration": 0.022351980209350586, 
            "status": "passed"
          }, 
          "step_type": "then"
        }, 
        {
          "keyword": "And", 
          "location": "features/StockSearchDisplay.feature:18", 
          "match": {
            "arguments": [
              {
                "name": "ElementName", 
                "value": "div_symbol"
              }, 
              {
                "name": "Value", 
                "value": "MCOT"
              }
            ], 
            "location": "../project-cylon/project_cylon/CommonSteps.py:103"
          }, 
          "name": "The [div_symbol] shows 'MCOT'", 
          "result": {
            "duration": 0.04744410514831543, 
            "status": "passed"
          }, 
          "step_type": "then"
        }, 
        {
          "keyword": "And", 
          "location": "features/StockSearchDisplay.feature:19", 
          "match": {
            "arguments": [
              {
                "name": "ElementName", 
                "value": "div_price"
              }, 
              {
                "name": "Value", 
                "value": "20.20"
              }
            ], 
            "location": "../project-cylon/project_cylon/CommonSteps.py:117"
          }, 
          "name": "The [div_price] more than '20.20'", 
          "result": {
            "duration": 0.050926923751831055, 
            "status": "passed"
          }, 
          "step_type": "then"
        }, 
        {
          "keyword": "And", 
          "location": "features/StockSearchDisplay.feature:20", 
          "match": {
            "arguments": [
              {
                "name": "ElementName", 
                "value": "div_price"
              }, 
              {
                "name": "Value", 
                "value": "37.25"
              }
            ], 
            "location": "../project-cylon/project_cylon/CommonSteps.py:131"
          }, 
          "name": "The [div_price] less than '37.25'", 
          "result": {
            "duration": 0.025691986083984375, 
            "status": "passed"
          }, 
          "step_type": "then"
        }
      ], 
      "tags": [
        "outline"
      ], 
      "type": "scenario"
    }
  ], 
  "keyword": "Feature", 
  "location": "features/StockSearchDisplay.feature:1", 
  "name": "Settrade stock search", 
  "status": "failed", 
  "tags": []
}
]
